MANIFEST.in
requirements.txt
setup.py
joker/__init__.py
joker/bioinfo/__init__.py
joker/bioinfo/replication.py
joker/bioinfo/translation.py
joker_bioinfo.egg-info/PKG-INFO
joker_bioinfo.egg-info/SOURCES.txt
joker_bioinfo.egg-info/dependency_links.txt
joker_bioinfo.egg-info/namespace_packages.txt
joker_bioinfo.egg-info/not-zip-safe
joker_bioinfo.egg-info/requires.txt
joker_bioinfo.egg-info/top_level.txt